[
    {
        "label": "cam_1",
        "roi": [
            77,
            85,
            270,
            400
        ]
    },
    {
        "label": "cam_2",
        "roi": [
            78,
            138,
            368,
            400
        ]
    },
    {
        "label": "cam_3",
        "roi": [
            45,
            118,
            358,
            400
        ]
    },
    {
        "label": "cam_4",
        "roi": [
            52,
            125,
            400,
            400
        ]
    },
    {
        "label": "cam_5",
        "roi": [
            17,
            123,
            393,
            398
        ]
    },
    {
        "label": "cam_6",
        "roi": [
            61,
            146,
            350,
            388
        ]
    }
]